{
  "titles": [
    {
      "id": "joshi-teki-seikatsu-2018",
      "title": "Joshi-teki Seikatsu! (2018)",
      "description": "Life as a Girl. Miki Ogawa vždy toužila žít jako půvabná dívka, a tak se přestěhovala z venkova do města, kde pracuje ve firmě s módou. Přestože vypadá jako krásná žena, skrývá tajemství – je transgender. Jednoho dne se setká s Tadaomim Gotem, bývalým spolužákem ze střední školy, který je překvapený její proměnou. Osud tomu chce, že se stanou spolubydlícími.",
      "labels": ["comedy", "transgender", "mtf"],
      "types": ["serie"],
      "languages": ["japanese", "cs-subs"],
      "items": [
        { "title": "s01e01", "link": "https://www.youtube.com/embed/" },
        { "title": "s01e02", "link": "https://www.youtube.com/embed/" },
        { "title": "s01e03", "link": "https://www.youtube.com/embed/" },
        { "title": "s01e04", "link": "https://www.youtube.com/embed/" }
       ],
      "runtime": "158 min",
      "imdb": "tt7701720",
      "creator": ["NHK"]
    },
    {
      "id": "tangerine-2015",
      "title": "Tangerine (2015)",
      "description": "After twenty-eight long days of absence, Sin-Dee is back on the block. It's Christmastime, and everyone wants to get into the festive spirit; however, Sin-Dee is in for a shock when she accidentally discovers that Chester, the love of her life, has been cheating on her. And to think that poor Sin-Dee has been making plans for the future. To save what's left of her dignity, heartbroken Sin-Dee embarks on a desperate mission to locate two-timing Chester, and no one can stop her--not even her best friend Alexandra, who vainly tries to be the voice of reason. Now, nothing can stand in the way of justice. After all, who wants to live a lie?",
      "labels": ["comedy", "drama", "prostitution", "transgender", "mtf"],
      "types": ["movie"],
      "languages": ["english", "cs-subs"],
      "items": [
        { "title": "movie", "link": "https://www.youtube.com/embed/" }
       ],
      "runtime": "88 min",
      "imdb": "tt3824458",
      "creator": ["Magnolia Pictures"]
    },
    {
      "id": "the-danish-girl-2015",
      "title": "The Danish Girl (2015)",
      "description": "A fictitious love story loosely inspired by the lives of Danish artists Lili Elbe and Gerda Wegener. Lili and Gerda's marriage and work evolve as they navigate Lili's groundbreaking journey as a transgender pioneer.",
      "labels": ["drama", "romantic", "transgender", "mtf"],
      "types": ["movie"],
      "languages": ["english", "cs-subs"],
      "items": [
        { "title": "movie", "link": "https://www.youtube.com/embed/" }
       ],
      "runtime": "119 min",
      "imdb": "tt0810819",
      "creator": ["Universal Pictures"]
    },
    {
      "id": "boy-meets-girl-2014",
      "title": "Boy Meets Girl (2014)",
      "description": "21-year-old Ricky is a transgender woman living in a small town in Kentucky with big dreams to move to New York and attend a school of fashion design. Ricky is working as a barista and spends most of her time hanging out with her only friend Robby, who has been by her side for the past 15 years. One day while Ricky is at work, Francesca, a woman from town, walks in and a friendship unexpectedly blossoms that then turns into an affair.",
      "labels": ["comedy", "romantic", "small-town", "transgender", "mtf"],
      "types": ["movie"],
      "languages": ["english", "cs-subs"],
      "items": [
        { "title": "movie", "link": "https://www.youtube.com/embed/M68o5yuAnFc?si=V9GQoj_O494Bvzag" }
       ],
      "runtime": "100 min",
      "imdb": "tt3007302",
      "creator": ["Wolfe Video"]
    },
    {
      "id": "himegoto-2014",
      "title": "Himegoto (2014)",
      "description": "Secret Princess. Hime Arikawa is on the run from loan sharks after inheriting his parents' debt. Dressed in a maid uniform is rescued by Shimoshina High's student council, they pay off his debt but demand he transfer schools and become their servant. Now forced to cross-dress, Hime must endure the trials of his new life while facing the challenges of his classmates.",
      "labels": ["comedy", "ecchi", "school", "crossdress"],
      "types": ["anime", "serie"],
      "languages": ["japanese", "en-subs"],
      "items": [
        { "title": "s01e01", "link": "https://www.youtube.com/embed/goMhyA9cTfI?si=vCYB8oK3G5HB9e1h" },
        { "title": "s01e02", "link": "https://www.youtube.com/embed/74PlTniQeWQ?si=04ry4DX_n8v-mSMk" },
        { "title": "s01e03", "link": "https://www.youtube.com/embed/yJzPKui_fhk?si=-nwQlvp8F7NMtDyu" },
        { "title": "s01e04", "link": "https://www.youtube.com/embed/" },
        { "title": "s01e05", "link": "https://www.youtube.com/embed/" },
        { "title": "s01e06", "link": "https://www.youtube.com/embed/" },
        { "title": "s01e07", "link": "https://www.youtube.com/embed/" },
        { "title": "s01e08", "link": "https://www.youtube.com/embed/" },
        { "title": "s01e09", "link": "https://www.youtube.com/embed/" },
        { "title": "s01e10", "link": "https://www.youtube.com/embed/" },
        { "title": "s01e11", "link": "https://www.youtube.com/embed/" },
        { "title": "s01e12", "link": "https://www.youtube.com/embed/" },
        { "title": "s01e13", "link": "https://www.youtube.com/embed/" }
       ],
      "runtime": "52 min",
      "imdb": "tt3639864",
      "creator": ["Asahi Production"]
    },
    {
      "id": "glen-or-glenda-1953",
      "title": "Glen or Glenda (1953)",
      "description": "A police inspector investigating the suicide of Patrick/Patricia consults Dr. Alton, who tells the story of Glen/Glenda. Glen, a transvestite but not homosexual, hides his identity from his fiancée, Barbara. Torn between honesty and fear, he dreams of his inner conflict. Finally, he confesses, and Barbara accepts him. Dr. Alton also recounts the story of Alan, a WWII veteran who transitioned into Anne through surgery.",
      "labels": ["documentary", "drama", "crossdress"],
      "types": ["movie"],
      "languages": ["english"],
      "items": [
        { "title": "movie", "link": "https://www.youtube.com/embed/jgvEvgYXa4o?si=HOwst9i9fXjIm0G7" }
       ],
      "runtime": "109 min",
      "imdb": "tt0045826",
      "creator": ["Screen Classics"]
    }
  ]
}
